pygal_maps_fr/__init__.py
pygal_maps_fr/fr.departments.svg
pygal_maps_fr/fr.regions.svg
pygal_maps_fr/maps.py
pygal_maps_fr/test/__init__.py
pygal_maps_fr/test/test_maps.py
pygal_maps_fr-1.1.0.dist-info/DESCRIPTION.rst
pygal_maps_fr-1.1.0.dist-info/METADATA
pygal_maps_fr-1.1.0.dist-info/RECORD
pygal_maps_fr-1.1.0.dist-info/WHEEL
pygal_maps_fr-1.1.0.dist-info/entry_points.txt
pygal_maps_fr-1.1.0.dist-info/metadata.json
pygal_maps_fr-1.1.0.dist-info/top_level.txt
