Metadata-Version: 2.0
Name: pygal-maps-fr
Version: 1.1.0
Summary: French maps for pygal
Home-page: http://pygal.org/
Author: Kozea
Author-email: florian.mounier@kozea.fr
License: GNU LGPL v3+
Keywords: svg,chart,graph,maps,french
Platform: Any
Classifier: Development Status :: 4 - Beta
Classifier: Environment :: Console
Classifier: Intended Audience :: End Users/Desktop
Classifier: License :: OSI Approved :: GNU Lesser General Public License v3 or later (LGPLv3+)
Classifier: Operating System :: OS Independent
Classifier: Programming Language :: Python :: 2
Classifier: Programming Language :: Python :: 3
Classifier: Topic :: Multimedia :: Graphics :: Presentation
Provides: pygal_maps_fr
Requires-Dist: pygal (>=1.9.9)
